flask_translator/__init__.py
flask_translator/translator.py
Flask_Translator-0.1.dist-info/LICENSE
Flask_Translator-0.1.dist-info/METADATA
Flask_Translator-0.1.dist-info/WHEEL
Flask_Translator-0.1.dist-info/top_level.txt
Flask_Translator-0.1.dist-info/RECORD
