Metadata-Version: 2.1
Name: Flask-Translator
Version: 0.1
Summary: Flask-Translator is a quick and easy-to-use extension for Flask projects, enabling translation from YAML files.
Home-page: https://github.com/inalbilal/flask-translator/
Author: Bilal Inal
Author-email: 01bilalinal@gmail.com
License: BSD
Keywords: Flask,Flask extension,translation,i18n,l10n,multilingual,language,internationalization,localization
Classifier: Environment :: Web Environment
Classifier: Intended Audience :: Developers
Classifier: License :: OSI Approved :: BSD License
Classifier: Operating System :: OS Independent
Classifier: Programming Language :: Python
Classifier: Topic :: Internet :: WWW/HTTP :: Dynamic Content
Classifier: Topic :: Software Development :: Libraries :: Python Modules
License-File: LICENSE
Requires-Dist: Flask
Requires-Dist: PyYAML
